arkhamdb/__init__.py
arkhamdb/api/__init__.py
arkhamdb/api/card/__init__.py
arkhamdb/api/card/routes.py
arkhamdb/api/card/schemas.py
arkhamdb/api/decklist/__init__.py
arkhamdb/api/decklist/routes.py
arkhamdb/api/decklist/schemas.py
arkhamdb/config.py
arkhamdb/console.py
arkhamdb/utils.py
arkhamdb-0.0.7.dist-info/entry_points.txt
arkhamdb-0.0.7.dist-info/LICENSE
arkhamdb-0.0.7.dist-info/WHEEL
arkhamdb-0.0.7.dist-info/METADATA
arkhamdb-0.0.7.dist-info/RECORD
