Metadata-Version: 2.1
Name: arkhamdb
Version: 0.0.7
Summary: Pythonic wrapper around the excellent ArkhamDB API. Designed to be standalone and importable to other projects.
Author: James Veitch
Author-email: 1722315+darth-veitcher@users.noreply.github.com
Requires-Python: >=3.9,<4.0
Classifier: License :: OSI Approved :: MIT License
Classifier: Programming Language :: Python :: 3
Classifier: Programming Language :: Python :: 3 :: Only
Classifier: Programming Language :: Python :: 3.10
Classifier: Programming Language :: Python :: 3.7
Classifier: Programming Language :: Python :: 3.8
Classifier: Programming Language :: Python :: 3.9
Classifier: Topic :: Software Development :: Libraries :: Python Modules
Requires-Dist: click (>=8.1.3,<9.0.0)
Requires-Dist: httpx (>=0.22.0,<0.23.0)
Requires-Dist: importlib-metadata (>=4.11.3,<5.0.0); python_version < "3.8"
Requires-Dist: pydantic (>=1.9.1,<2.0.0)
Project-URL: Documentation, https://arkhamdb.readthedocs.io
